setup.py
machi/__init__.py
machi/machi.py
machi.egg-info/PKG-INFO
machi.egg-info/SOURCES.txt
machi.egg-info/dependency_links.txt
machi.egg-info/not-zip-safe
machi.egg-info/requires.txt
machi.egg-info/top_level.txt