Metadata-Version: 1.0
Name: machi
Version: 1.1.1
Summary: Machina Time Series Generation and Backtesting
Home-page: https://machi.na
Author: Akram Kamal
Author-email: akamal@machi.na
License: MIT
Platform: UNKNOWN
